pyfony/container/PyfonyHook.py
pyfony/kernel/BaseKernel.py
pyfony/kernel/BaseKernelTest/config_dev.yaml
pyfony/kernel/BaseKernelTest.py
pyfony-0.6.1.dist-info/LICENSE
pyfony-0.6.1.dist-info/WHEEL
pyfony-0.6.1.dist-info/METADATA
pyfony-0.6.1.dist-info/RECORD
