Metadata-Version: 2.1
Name: pyfony
Version: 0.6.1
Summary: Dependency Injection powered framework
Home-page: https://github.com/pyfony/pyfony
License: MIT
Author: Jiri Koutny
Author-email: jiri.koutny@datasentics.com
Requires-Python: >=3.7.3,<3.8.0
Classifier: License :: OSI Approved :: MIT License
Classifier: Operating System :: OS Independent
Classifier: Programming Language :: Python :: 3
Requires-Dist: console-bundle (>=0.2.5,<0.3.0)
Requires-Dist: injecta (>=0.8.11,<0.9.0)
Requires-Dist: logger-bundle (>=0.5.3,<0.6.0)
Requires-Dist: pyfony-bundles (>=0.2.4,<0.3.0)
Project-URL: Repository, https://github.com/pyfony/pyfony
